flowire_sdk/__init__.py
flowire_sdk/node_base.py
flowire_sdk/stream_handler.py
flowire_sdk-0.0.1a2.dist-info/METADATA
flowire_sdk-0.0.1a2.dist-info/WHEEL
flowire_sdk-0.0.1a2.dist-info/licenses/LICENSE
flowire_sdk-0.0.1a2.dist-info/RECORD
