Metadata-Version: 2.4
Name: flowire-sdk
Version: 0.0.1a2
Summary: SDK for building Flowire workflow nodes
License-Expression: MIT
License-File: LICENSE
Requires-Python: >=3.11
Requires-Dist: pydantic>=2.5.0
Provides-Extra: dev
Requires-Dist: pytest-asyncio>=0.23.0; extra == 'dev'
Requires-Dist: pytest>=8.0.0; extra == 'dev'
Requires-Dist: ruff>=0.4.0; extra == 'dev'
